aaaa/42
aaaa/__init__.py
aaaa/ahordat.py
aaaa/demo.py
aaaahorodatage-0.0.1.dist-info/LICENCE
aaaahorodatage-0.0.1.dist-info/METADATA
aaaahorodatage-0.0.1.dist-info/WHEEL
aaaahorodatage-0.0.1.dist-info/top_level.txt
aaaahorodatage-0.0.1.dist-info/RECORD
