Metadata-Version: 2.1
Name: aaaahorodatage
Version: 0.0.1
Summary: Module python 3 de gestion d'horodatages. Chaque horodatage embarque son époque de référence et son fuseau horaire. L'époque de référence est configurable et peut être différente de l'époque Unix (1970-01-01T00:00:00) .
Home-page: https://framagit.org/zenjo/AaaaHorodatage
Author: Robert Sebille
Author-email: robert@sebille.name
Maintainer: Robert Sebille
Maintainer-email: robert@sebille.name
License: GNU GPL
Download-URL: https://framagit.org/zenjo/AaaaHorodatage/tree/master
Platform: UNKNOWN
Classifier: Programming Language :: Python :: 3
Classifier: License :: OSI Approved :: GNU General Public License (GPL)
Classifier: Operating System :: OS Independent
